README
memcache.py
setup.py
appengine_utils/__init__.py
appengine_utils/appengine_settings.py
appengine_utils/mail.py
appengine_utils/storage.py
appengine_utils/test_utils.py
appengine_utils/views.py
django_appengine_utils.egg-info/PKG-INFO
django_appengine_utils.egg-info/SOURCES.txt
django_appengine_utils.egg-info/dependency_links.txt
django_appengine_utils.egg-info/not-zip-safe
django_appengine_utils.egg-info/requires.txt
django_appengine_utils.egg-info/top_level.txt